LICENSE.txt
MANIFEST.in
README.rst
setup.cfg
setup.py
readyrector/__init__.py
readyrector/forms.py
readyrector/middleware.py
readyrector/models.py
readyrector/validators.py
readyrector.egg-info/PKG-INFO
readyrector.egg-info/SOURCES.txt
readyrector.egg-info/dependency_links.txt
readyrector.egg-info/not-zip-safe
readyrector.egg-info/requires.txt
readyrector.egg-info/top_level.txt
readyrector/locale/nl/LC_MESSAGES/django.mo
readyrector/locale/nl/LC_MESSAGES/django.po
readyrector/migrations/0001_initial.py
readyrector/migrations/__init__.py